bohydra/__init__.py
bohydra/covariances.py
bohydra/emulators.py
bohydra/mpi_optimizers.py
bohydra/optimizers.py
bohydra/utils.py
bohydra-0.1.2.dist-info/licenses/LICENSE
bohydra-0.1.2.dist-info/METADATA
bohydra-0.1.2.dist-info/WHEEL
bohydra-0.1.2.dist-info/top_level.txt
bohydra-0.1.2.dist-info/RECORD
