Metadata-Version: 2.4
Name: bohydra
Version: 0.1.2
Summary: Multifidelity Bayesian optimization with serial and MPI-enabled (parallel, asynchronous) workflows.
Author-email: Mike Grosskopf <mikegros@lanl.gov>
License: This program is Open-Source under the BSD-3 License.
Project-URL: Homepage, https://github.com/lanl/bohydra
Project-URL: Repository, https://github.com/lanl/bohydra
Project-URL: Bug Tracker, https://github.com/lanl/bohydra/issues
Keywords: bayesian-optimization,gaussian-process,multi-fidelity,mpi,asynchronous
Requires-Python: >=3.9
License-File: LICENSE
Requires-Dist: numpy>=1.20
Requires-Dist: scipy>=1.7
Requires-Dist: scikit-learn>=1.0
Provides-Extra: mpi
Requires-Dist: mpi4py>=3.1; extra == "mpi"
Requires-Dist: pandas>=1.3; extra == "mpi"
Requires-Dist: pyDOE>=0.3.8; extra == "mpi"
Provides-Extra: examples
Requires-Dist: pandas>=1.3; extra == "examples"
Requires-Dist: pyDOE>=0.3.8; extra == "examples"
Dynamic: license-file
